README.rst
setup.py
serfclient/__init__.py
serfclient/client.py
serfclient/connection.py
serfclient/environment_config.py
serfclient/result.py
serfclient.egg-info/PKG-INFO
serfclient.egg-info/SOURCES.txt
serfclient.egg-info/dependency_links.txt
serfclient.egg-info/requires.txt
serfclient.egg-info/top_level.txt