Metadata-Version: 1.0
Name: serfclient
Version: 0.6.0
Summary: Python client for the Serf orchestration tool
Home-page: https://github.com/KushalP/serfclient-py
Author: Kushal Pisavadia
Author-email: kushal@violentlymild.com
License: MIT
Keywords: Serf,orchestration,service discovery
Platform: UNKNOWN
